{
  "pages": [
    {
      "id": "01",
      "tag": "portraits",
      "name": "Mizuki",
      "date": "2019.09",
      "imgNum": 11
    },
    {
      "id": "02",
      "tag": "portraits",
      "name": "Kanako & Akanen",
      "date": "2019.11",
      "imgNum": 13
    },
    {
      "id": "03",
      "tag": "portraits",
      "name": "Akanen",
      "date": "2019.12",
      "imgNum": 9
    },
    {
      "id": "04",
      "tag": "works",
      "name": "Yurie Matsugi",
      "work": "Bigakuseizukan",
      "link": "https://bigakusei.com/binan-bijo/24719/",
      "imgNum": 6

    },
    {
      "id": "05",
      "tag": "works",
      "name": "Yurina Takagi",
      "work": "Bigakuseizukan",
      "link": "https://bigakusei.com/binan-bijo/24733/",
      "imgNum": 5
    }
  ]
}
